switchenv/__init__.py
switchenv/blob_location.json
switchenv/switchenv.py
switchenv/version.py
switchenv/tests/__init__.py
switchenv/tests/tests.py
switchenv-0.3.2.dist-info/METADATA
switchenv-0.3.2.dist-info/WHEEL
switchenv-0.3.2.dist-info/entry_points.txt
switchenv-0.3.2.dist-info/licenses/LICENSE
switchenv-0.3.2.dist-info/RECORD
