Metadata-Version: 2.4
Name: switchenv
Version: 0.3.2
Summary: Manager for bash environments
Project-URL: Homepage, https://github.com/robdmc/switchenv
Project-URL: Repository, https://github.com/robdmc/switchenv
Author-email: Rob deCarvalho <unlisted@unlisted.net>
License-Expression: MIT
License-File: LICENSE
Classifier: Intended Audience :: Developers
Classifier: License :: OSI Approved :: MIT License
Classifier: Operating System :: OS Independent
Classifier: Programming Language :: Python :: 3.12
Requires-Python: >=3.12
Requires-Dist: click
Requires-Dist: fuzzypicker
Provides-Extra: dev
Requires-Dist: coverage; extra == 'dev'
Requires-Dist: flake8; extra == 'dev'
Requires-Dist: mock; extra == 'dev'
Requires-Dist: nose; extra == 'dev'
Requires-Dist: sphinx; extra == 'dev'
Requires-Dist: sphinx-rtd-theme; extra == 'dev'
Requires-Dist: twine; extra == 'dev'
Requires-Dist: wheel; extra == 'dev'
